honeio/__version__.py
honeio/constants.cpython-312-x86_64-linux-gnu.so
honeio/functions/general.cpython-312-x86_64-linux-gnu.so
honeio/functions/hamiltonian.cpython-312-x86_64-linux-gnu.so
honeio/initialization/normal.cpython-312-x86_64-linux-gnu.so
honeio/initialization/validate_inputs.cpython-312-x86_64-linux-gnu.so
honeio/integrations/sklearn/hooks.cpython-312-x86_64-linux-gnu.so
honeio/integrations/sklearn/hooks.pyi
honeio/integrations/sklearn/qcmlsklearn.cpython-312-x86_64-linux-gnu.so
honeio/integrations/sklearn/qcmlsklearn.pyi
honeio/integrations/sklearn/test_qcmlsklearn.cpython-312-x86_64-linux-gnu.so
honeio/integrations/sklearn/test_qcmlsklearn.pyi
honeio/layers/_retarrgykkj0iz1.cpython-312-x86_64-linux-gnu.so
honeio/layers/dropout.cpython-312-x86_64-linux-gnu.so
honeio/layers/general.cpython-312-x86_64-linux-gnu.so
honeio/layers/weighted.cpython-312-x86_64-linux-gnu.so
honeio/linalg/lobpcg.cpython-312-x86_64-linux-gnu.so
honeio/linalg/regularized_eigh.cpython-312-x86_64-linux-gnu.so
honeio/linalg/state_solver.cpython-312-x86_64-linux-gnu.so
hone_io_enterprise-2.3.0.dist-info/METADATA
hone_io_enterprise-2.3.0.dist-info/WHEEL
hone_io_enterprise-2.3.0.dist-info/top_level.txt
hone_io_enterprise-2.3.0.dist-info/RECORD
