Metadata-Version: 2.4
Name: hone-io-enterprise
Version: 2.3.0
Summary: Library for quantum cognition machine learning.
Requires-Python: >=3.12
Requires-Dist: torch==2.7.0
Requires-Dist: structlog>=24.4.0
Requires-Dist: pandas>=2.2.3
Requires-Dist: qbism>=0.1.0
Requires-Dist: numpy>=2.1.3
Requires-Dist: rich
Requires-Dist: scikit-learn
Requires-Dist: sentry_sdk
Requires-Dist: tensordict>=0.7.2
Requires-Dist: cryptlex-lexactivator>=3.33.0
Requires-Dist: cachetools>=6.1.0
Requires-Dist: pywavelets>=1.9.0
Requires-Dist: tqdm>=4.67.1
